AUTHORS.rst
CHANGELOG.rst
LICENSE
MANIFEST.in
README.rst
setup.py
django_insight.egg-info/PKG-INFO
django_insight.egg-info/SOURCES.txt
django_insight.egg-info/dependency_links.txt
django_insight.egg-info/not-zip-safe
django_insight.egg-info/requires.txt
django_insight.egg-info/top_level.txt
insight/__init__.py
insight/admin.py
insight/models.py
insight/signals.py
insight/tests.py
insight/urls.py
insight/views.py
insight/migrations/0001_initial.py
insight/migrations/0002_auto__add_field_origin_redirect_to.py
insight/migrations/0003_auto__add_field_origin_track_registrations.py
insight/migrations/__init__.py
insight/static/admin/css/splitscreen.css
insight/static/admin/js/graphs.js
insight/static/admin/thirdparty/d3.v2.min.js
insight/templates/admin/insight/app_index.html
insight/templates/admin/insight/change_list.html
insight/templates/admin/insight/origin/change_list.html
insight/templates/admin/insight/registration/change_form.html
insight/templates/admin/insight/registration/change_list.html
insight/test/__init__.py
insight/test/models.py
insight/test/urls.py